nautobot_utsc/__init__.py
nautobot_utsc/diffsync/__init__.py
nautobot_utsc/diffsync/bluecat/__init__.py
nautobot_utsc/diffsync/bluecat/adapters.py
nautobot_utsc/diffsync/bluecat/models.py
nautobot_utsc/diffsync/yaml/__init__.py
nautobot_utsc/diffsync/yaml/adapters.py
nautobot_utsc/diffsync/yaml/models.py
nautobot_utsc/diffsync/yaml/test.yaml
nautobot_utsc/jobs.py
nautobot_utsc/nautobot_config.py
utsc.nautobot-2022.4.26.1.dist-info/WHEEL
utsc.nautobot-2022.4.26.1.dist-info/METADATA
utsc.nautobot-2022.4.26.1.dist-info/RECORD
