Metadata-Version: 2.1
Name: utsc.nautobot
Version: 2022.4.26.1
Summary: A collection of UTSC-specific modifications and extensions to Nautobot.
License: MIT
Author: Alex Tremblay
Author-email: alex.tremblay@utoronto.ca
Requires-Python: >=3.10,<4.0
Classifier: License :: OSI Approved :: MIT License
Classifier: Programming Language :: Python :: 3
Classifier: Programming Language :: Python :: 3.10
Requires-Dist: debugpy
Requires-Dist: django-auth-ldap
Requires-Dist: django-debug-toolbar
Requires-Dist: html-table-parser-python3 (>=0.2.0)
Requires-Dist: nautobot (>=1.3)
Requires-Dist: nautobot_ssot (>=1.1.0)
Requires-Dist: utsc.core
